odoo/addons/login_all_company/README.rst
odoo/addons/login_all_company/__init__.py
odoo/addons/login_all_company/__manifest__.py
odoo/addons/login_all_company/i18n/it.po
odoo/addons/login_all_company/i18n/login_all_company.pot
odoo/addons/login_all_company/readme/CONTRIBUTORS.md
odoo/addons/login_all_company/readme/DESCRIPTION.md
odoo/addons/login_all_company/static/description/icon.png
odoo/addons/login_all_company/static/description/index.html
odoo/addons/login_all_company/static/src/js/company_service.esm.js
odoo_addon_login_all_company-18.0.0.0.0.2.dist-info/METADATA
odoo_addon_login_all_company-18.0.0.0.0.2.dist-info/WHEEL
odoo_addon_login_all_company-18.0.0.0.0.2.dist-info/top_level.txt
odoo_addon_login_all_company-18.0.0.0.0.2.dist-info/RECORD
