Metadata-Version: 2.1
Name: odoo-addon-login_all_company
Version: 18.0.0.0.0.2
Requires-Python: >=3.10
Requires-Dist: odoo==18.0.*
Summary: Access all your companies when you log in
Home-page: https://github.com/OCA/multi-company
License: AGPL-3
Author: Creu Blanca,Odoo Community Association (OCA)
Author-email: support@odoo-community.org
Classifier: Programming Language :: Python
Classifier: Framework :: Odoo
Classifier: Framework :: Odoo :: 18.0
Classifier: License :: OSI Approved :: GNU Affero General Public License v3
